{
  "crm": {
    "moduleId": "crm",
    "moduleName": "Customer Relationship Management",
    "menus": [
      {
        "id": "dashboard",
        "label": "Dashboard",
        "path": "/",
        "icon": "HomeIcon",
        "order": 1
      },
      {
        "id": "customers",
        "label": "Customer Management",
        "icon": "UsersIcon",
        "order": 2,
        "children": [
          {
            "id": "customer-list",
            "label": "View Customers",
            "path": "/customers",
            "order": 1
          },
          {
            "id": "create-customer",
            "label": "Create Customer",
            "path": "/customers/create",
            "order": 2
          },
          {
            "id": "import-customers",
            "label": "Import Customers",
            "path": "/customers/import",
            "order": 3
          },
          {
            "id": "customer-segments",
            "label": "Customer Segments",
            "path": "/customers/segments",
            "order": 4
          },
          {
            "id": "customer-analytics",
            "label": "Customer Analytics",
            "path": "/customers/analytics",
            "order": 5
          }
        ]
      },
      {
        "id": "leads",
        "label": "Lead Management",
        "icon": "MagnifyingGlassIcon",
        "order": 3,
        "children": [
          {
            "id": "leads-list",
            "label": "View Leads",
            "path": "/leads",
            "order": 1
          },
          {
            "id": "create-lead",
            "label": "Create Lead",
            "path": "/leads/create",
            "order": 2
          },
          {
            "id": "lead-scoring",
            "label": "Lead Scoring",
            "path": "/leads/scoring",
            "order": 3
          },
          {
            "id": "lead-conversion",
            "label": "Lead Conversion",
            "path": "/leads/conversion",
            "order": 4
          },
          {
            "id": "lead-campaigns",
            "label": "Marketing Campaigns",
            "path": "/leads/campaigns",
            "order": 5
          }
        ]
      },
      {
        "id": "opportunities",
        "label": "Sales Pipeline",
        "icon": "ChartBarIcon",
        "order": 4,
        "children": [
          {
            "id": "opportunities-list",
            "label": "View Opportunities",
            "path": "/opportunities",
            "order": 1
          },
          {
            "id": "create-opportunity",
            "label": "Create Opportunity",
            "path": "/opportunities/create",
            "order": 2
          },
          {
            "id": "pipeline-management",
            "label": "Pipeline Management",
            "path": "/opportunities/pipeline",
            "order": 3
          },
          {
            "id": "deal-forecasting",
            "label": "Deal Forecasting",
            "path": "/opportunities/forecasting",
            "order": 4
          },
          {
            "id": "win-loss-analysis",
            "label": "Win/Loss Analysis",
            "path": "/opportunities/analysis",
            "order": 5
          }
        ]
      },
      {
        "id": "reports",
        "label": "Reports & Analytics",
        "icon": "DocumentChartBarIcon",
        "order": 5,
        "children": [
          {
            "id": "sales-reports",
            "label": "Sales Reports",
            "path": "/reports/sales",
            "order": 1
          },
          {
            "id": "performance-reports",
            "label": "Performance Reports",
            "path": "/reports/performance",
            "order": 2
          },
          {
            "id": "revenue-analytics",
            "label": "Revenue Analytics",
            "path": "/reports/revenue",
            "order": 3
          },
          {
            "id": "custom-reports",
            "label": "Custom Reports",
            "path": "/reports/custom",
            "order": 4
          },
          {
            "id": "export-data",
            "label": "Export Data",
            "path": "/reports/export",
            "order": 5
          }
        ]
      },
      {
        "id": "settings",
        "label": "CRM Settings",
        "icon": "CogIcon",
        "order": 6,
        "children": [
          {
            "id": "sales-process",
            "label": "Sales Process Config",
            "path": "/settings/process",
            "order": 1
          },
          {
            "id": "lead-sources",
            "label": "Lead Sources",
            "path": "/settings/sources",
            "order": 2
          },
          {
            "id": "email-templates",
            "label": "Email Templates",
            "path": "/settings/templates",
            "order": 3
          },
          {
            "id": "automation-rules",
            "label": "Automation Rules",
            "path": "/settings/automation",
            "order": 4
          },
          {
            "id": "integration-settings",
            "label": "Integrations",
            "path": "/settings/integrations",
            "order": 5
          }
        ]
      }
    ]
  },
  "inventory": {
    "moduleId": "inventory",
    "moduleName": "Inventory Management",
    "menus": [
      {
        "id": "dashboard",
        "label": "Dashboard",
        "path": "/",
        "icon": "HomeIcon",
        "order": 1
      },
      {
        "id": "products",
        "label": "Product Management",
        "icon": "CubeIcon",
        "order": 2,
        "children": [
          {
            "id": "products-list",
            "label": "View Products",
            "path": "/products",
            "order": 1
          },
          {
            "id": "create-product",
            "label": "Add Product",
            "path": "/products/create",
            "order": 2
          },
          {
            "id": "product-categories",
            "label": "Categories",
            "path": "/products/categories",
            "order": 3
          },
          {
            "id": "product-attributes",
            "label": "Product Attributes",
            "path": "/products/attributes",
            "order": 4
          },
          {
            "id": "bulk-import",
            "label": "Bulk Import",
            "path": "/products/import",
            "order": 5
          },
          {
            "id": "product-variants",
            "label": "Product Variants",
            "path": "/products/variants",
            "order": 6
          }
        ]
      },
      {
        "id": "stock",
        "label": "Stock Management",
        "icon": "ArchiveBoxIcon",
        "order": 3,
        "children": [
          {
            "id": "stock-levels",
            "label": "Stock Levels",
            "path": "/stock",
            "order": 1
          },
          {
            "id": "stock-adjustment",
            "label": "Stock Adjustment",
            "path": "/stock/adjustment",
            "order": 2
          },
          {
            "id": "low-stock-alerts",
            "label": "Low Stock Alerts",
            "path": "/stock/alerts",
            "order": 3
          },
          {
            "id": "stock-transfer",
            "label": "Stock Transfer",
            "path": "/stock/transfer",
            "order": 4
          },
          {
            "id": "stock-audit",
            "label": "Stock Audit",
            "path": "/stock/audit",
            "order": 5
          },
          {
            "id": "reorder-points",
            "label": "Reorder Points",
            "path": "/stock/reorder",
            "order": 6
          }
        ]
      },
      {
        "id": "warehouses",
        "label": "Warehouse Management",
        "icon": "BuildingStorefrontIcon",
        "order": 4,
        "children": [
          {
            "id": "warehouses-list",
            "label": "Warehouses",
            "path": "/warehouses",
            "order": 1
          },
          {
            "id": "warehouse-locations",
            "label": "Storage Locations",
            "path": "/warehouses/locations",
            "order": 2
          },
          {
            "id": "warehouse-zones",
            "label": "Warehouse Zones",
            "path": "/warehouses/zones",
            "order": 3
          },
          {
            "id": "receiving",
            "label": "Receiving",
            "path": "/warehouses/receiving",
            "order": 4
          },
          {
            "id": "picking",
            "label": "Order Picking",
            "path": "/warehouses/picking",
            "order": 5
          }
        ]
      },
      {
        "id": "suppliers",
        "label": "Supplier Management",
        "icon": "TruckIcon",
        "order": 5,
        "children": [
          {
            "id": "suppliers-list",
            "label": "Suppliers",
            "path": "/suppliers",
            "order": 1
          },
          {
            "id": "create-supplier",
            "label": "Add Supplier",
            "path": "/suppliers/create",
            "order": 2
          },
          {
            "id": "supplier-contracts",
            "label": "Contracts",
            "path": "/suppliers/contracts",
            "order": 3
          },
          {
            "id": "supplier-performance",
            "label": "Performance",
            "path": "/suppliers/performance",
            "order": 4
          },
          {
            "id": "purchase-orders",
            "label": "Purchase Orders",
            "path": "/suppliers/orders",
            "order": 5
          }
        ]
      },
      {
        "id": "reports",
        "label": "Inventory Reports",
        "icon": "DocumentChartBarIcon",
        "order": 6,
        "children": [
          {
            "id": "stock-reports",
            "label": "Stock Reports",
            "path": "/reports/stock",
            "order": 1
          },
          {
            "id": "movement-reports",
            "label": "Movement Reports",
            "path": "/reports/movement",
            "order": 2
          },
          {
            "id": "valuation-reports",
            "label": "Valuation Reports",
            "path": "/reports/valuation",
            "order": 3
          },
          {
            "id": "abc-analysis",
            "label": "ABC Analysis",
            "path": "/reports/abc",
            "order": 4
          },
          {
            "id": "turnover-analysis",
            "label": "Turnover Analysis",
            "path": "/reports/turnover",
            "order": 5
          }
        ]
      }
    ]
  },
  "hr": {
    "moduleId": "hr",
    "moduleName": "Human Resources",
    "menus": [
      {
        "id": "dashboard",
        "label": "Dashboard",
        "path": "/",
        "icon": "HomeIcon",
        "order": 1
      },
      {
        "id": "employees",
        "label": "Employee Management",
        "icon": "UsersIcon",
        "order": 2,
        "children": [
          {
            "id": "employees-list",
            "label": "Employee Directory",
            "path": "/employees",
            "order": 1
          },
          {
            "id": "create-employee",
            "label": "Add Employee",
            "path": "/employees/create",
            "order": 2
          },
          {
            "id": "employee-profiles",
            "label": "Employee Profiles",
            "path": "/employees/profiles",
            "order": 3
          },
          {
            "id": "org-chart",
            "label": "Organization Chart",
            "path": "/employees/org-chart",
            "order": 4
          },
          {
            "id": "employee-documents",
            "label": "Employee Documents",
            "path": "/employees/documents",
            "order": 5
          },
          {
            "id": "emergency-contacts",
            "label": "Emergency Contacts",
            "path": "/employees/emergency",
            "order": 6
          }
        ]
      },
      {
        "id": "attendance",
        "label": "Attendance & Time",
        "icon": "ClockIcon",
        "order": 3,
        "children": [
          {
            "id": "attendance-tracking",
            "label": "Attendance Tracking",
            "path": "/attendance",
            "order": 1
          },
          {
            "id": "time-sheets",
            "label": "Time Sheets",
            "path": "/attendance/timesheets",
            "order": 2
          },
          {
            "id": "work-schedules",
            "label": "Work Schedules",
            "path": "/attendance/schedules",
            "order": 3
          },
          {
            "id": "overtime-management",
            "label": "Overtime Management",
            "path": "/attendance/overtime",
            "order": 4
          },
          {
            "id": "attendance-reports",
            "label": "Attendance Reports",
            "path": "/attendance/reports",
            "order": 5
          },
          {
            "id": "time-off-requests",
            "label": "Time Off Requests",
            "path": "/attendance/time-off",
            "order": 6
          }
        ]
      },
      {
        "id": "leave",
        "label": "Leave Management",
        "icon": "CalendarDaysIcon",
        "order": 4,
        "children": [
          {
            "id": "leave-requests",
            "label": "Leave Requests",
            "path": "/leave/requests",
            "order": 1
          },
          {
            "id": "leave-approval",
            "label": "Leave Approvals",
            "path": "/leave/approvals",
            "order": 2
          },
          {
            "id": "leave-calendar",
            "label": "Leave Calendar",
            "path": "/leave/calendar",
            "order": 3
          },
          {
            "id": "leave-policies",
            "label": "Leave Policies",
            "path": "/leave/policies",
            "order": 4
          },
          {
            "id": "holiday-calendar",
            "label": "Holiday Calendar",
            "path": "/leave/holidays",
            "order": 5
          },
          {
            "id": "leave-balance",
            "label": "Leave Balance",
            "path": "/leave/balance",
            "order": 6
          }
        ]
      },
      {
        "id": "payroll",
        "label": "Payroll Management",
        "icon": "CurrencyDollarIcon",
        "order": 5,
        "children": [
          {
            "id": "payroll-processing",
            "label": "Payroll Processing",
            "path": "/payroll/processing",
            "order": 1
          },
          {
            "id": "salary-structure",
            "label": "Salary Structure",
            "path": "/payroll/salary",
            "order": 2
          },
          {
            "id": "pay-slips",
            "label": "Pay Slips",
            "path": "/payroll/payslips",
            "order": 3
          },
          {
            "id": "tax-management",
            "label": "Tax Management",
            "path": "/payroll/tax",
            "order": 4
          },
          {
            "id": "benefits-deductions",
            "label": "Benefits & Deductions",
            "path": "/payroll/benefits",
            "order": 5
          },
          {
            "id": "payroll-reports",
            "label": "Payroll Reports",
            "path": "/payroll/reports",
            "order": 6
          }
        ]
      },
      {
        "id": "performance",
        "label": "Performance Management",
        "icon": "ChartBarIcon",
        "order": 6,
        "children": [
          {
            "id": "performance-reviews",
            "label": "Performance Reviews",
            "path": "/performance/reviews",
            "order": 1
          },
          {
            "id": "goal-setting",
            "label": "Goal Setting",
            "path": "/performance/goals",
            "order": 2
          },
          {
            "id": "360-feedback",
            "label": "360° Feedback",
            "path": "/performance/feedback",
            "order": 3
          },
          {
            "id": "performance-metrics",
            "label": "Performance Metrics",
            "path": "/performance/metrics",
            "order": 4
          },
          {
            "id": "development-plans",
            "label": "Development Plans",
            "path": "/performance/development",
            "order": 5
          },
          {
            "id": "career-planning",
            "label": "Career Planning",
            "path": "/performance/career",
            "order": 6
          }
        ]
      },
      {
        "id": "recruitment",
        "label": "Recruitment",
        "icon": "UserPlusIcon",
        "order": 7,
        "children": [
          {
            "id": "job-postings",
            "label": "Job Postings",
            "path": "/recruitment/jobs",
            "order": 1
          },
          {
            "id": "applicant-tracking",
            "label": "Applicant Tracking",
            "path": "/recruitment/applicants",
            "order": 2
          },
          {
            "id": "interview-scheduling",
            "label": "Interview Scheduling",
            "path": "/recruitment/interviews",
            "order": 3
          },
          {
            "id": "candidate-assessment",
            "label": "Candidate Assessment",
            "path": "/recruitment/assessment",
            "order": 4
          },
          {
            "id": "onboarding",
            "label": "Onboarding",
            "path": "/recruitment/onboarding",
            "order": 5
          },
          {
            "id": "recruitment-reports",
            "label": "Recruitment Reports",
            "path": "/recruitment/reports",
            "order": 6
          }
        ]
      }
    ]
  },
  "finance": {
    "moduleId": "finance",
    "moduleName": "Finance Management",
    "menus": [
      {
        "id": "dashboard",
        "label": "Dashboard",
        "path": "/",
        "icon": "HomeIcon",
        "order": 1
      },
      {
        "id": "accounts",
        "label": "Account Management",
        "icon": "BanknotesIcon",
        "order": 2,
        "children": [
          {
            "id": "chart-of-accounts",
            "label": "Chart of Accounts",
            "path": "/accounts",
            "order": 1
          },
          {
            "id": "create-account",
            "label": "Create Account",
            "path": "/accounts/create",
            "order": 2
          },
          {
            "id": "account-reconciliation",
            "label": "Account Reconciliation",
            "path": "/accounts/reconciliation",
            "order": 3
          },
          {
            "id": "bank-accounts",
            "label": "Bank Accounts",
            "path": "/accounts/banks",
            "order": 4
          },
          {
            "id": "credit-cards",
            "label": "Credit Cards",
            "path": "/accounts/credit-cards",
            "order": 5
          },
          {
            "id": "cash-accounts",
            "label": "Cash Accounts",
            "path": "/accounts/cash",
            "order": 6
          }
        ]
      },
      {
        "id": "invoicing",
        "label": "Invoicing & Billing",
        "icon": "DocumentTextIcon",
        "order": 3,
        "children": [
          {
            "id": "invoices-list",
            "label": "Invoices",
            "path": "/invoices",
            "order": 1
          },
          {
            "id": "create-invoice",
            "label": "Create Invoice",
            "path": "/invoices/create",
            "order": 2
          },
          {
            "id": "recurring-invoices",
            "label": "Recurring Invoices",
            "path": "/invoices/recurring",
            "order": 3
          },
          {
            "id": "invoice-templates",
            "label": "Invoice Templates",
            "path": "/invoices/templates",
            "order": 4
          },
          {
            "id": "payment-tracking",
            "label": "Payment Tracking",
            "path": "/invoices/payments",
            "order": 5
          },
          {
            "id": "credit-notes",
            "label": "Credit Notes",
            "path": "/invoices/credit-notes",
            "order": 6
          }
        ]
      },
      {
        "id": "expenses",
        "label": "Expense Management",
        "icon": "ReceiptPercentIcon",
        "order": 4,
        "children": [
          {
            "id": "expenses-list",
            "label": "Expenses",
            "path": "/expenses",
            "order": 1
          },
          {
            "id": "create-expense",
            "label": "Record Expense",
            "path": "/expenses/create",
            "order": 2
          },
          {
            "id": "expense-categories",
            "label": "Expense Categories",
            "path": "/expenses/categories",
            "order": 3
          },
          {
            "id": "expense-approval",
            "label": "Expense Approval",
            "path": "/expenses/approval",
            "order": 4
          },
          {
            "id": "expense-reports",
            "label": "Expense Reports",
            "path": "/expenses/reports",
            "order": 5
          },
          {
            "id": "mileage-tracking",
            "label": "Mileage Tracking",
            "path": "/expenses/mileage",
            "order": 6
          }
        ]
      },
      {
        "id": "budgeting",
        "label": "Budget Planning",
        "icon": "CalculatorIcon",
        "order": 5,
        "children": [
          {
            "id": "budgets-list",
            "label": "Budgets",
            "path": "/budgets",
            "order": 1
          },
          {
            "id": "create-budget",
            "label": "Create Budget",
            "path": "/budgets/create",
            "order": 2
          },
          {
            "id": "budget-vs-actual",
            "label": "Budget vs Actual",
            "path": "/budgets/comparison",
            "order": 3
          },
          {
            "id": "budget-forecasting",
            "label": "Budget Forecasting",
            "path": "/budgets/forecasting",
            "order": 4
          },
          {
            "id": "cost-centers",
            "label": "Cost Centers",
            "path": "/budgets/cost-centers",
            "order": 5
          },
          {
            "id": "budget-approval",
            "label": "Budget Approval",
            "path": "/budgets/approval",
            "order": 6
          }
        ]
      },
      {
        "id": "reports",
        "label": "Financial Reports",
        "icon": "DocumentChartBarIcon",
        "order": 6,
        "children": [
          {
            "id": "profit-loss",
            "label": "Profit & Loss",
            "path": "/reports/profit-loss",
            "order": 1
          },
          {
            "id": "balance-sheet",
            "label": "Balance Sheet",
            "path": "/reports/balance-sheet",
            "order": 2
          },
          {
            "id": "cash-flow",
            "label": "Cash Flow Statement",
            "path": "/reports/cash-flow",
            "order": 3
          },
          {
            "id": "trial-balance",
            "label": "Trial Balance",
            "path": "/reports/trial-balance",
            "order": 4
          },
          {
            "id": "aging-reports",
            "label": "Aging Reports",
            "path": "/reports/aging",
            "order": 5
          },
          {
            "id": "tax-reports",
            "label": "Tax Reports",
            "path": "/reports/tax",
            "order": 6
          },
          {
            "id": "custom-reports",
            "label": "Custom Reports",
            "path": "/reports/custom",
            "order": 7
          }
        ]
      },
      {
        "id": "settings",
        "label": "Finance Settings",
        "icon": "CogIcon",
        "order": 7,
        "children": [
          {
            "id": "company-settings",
            "label": "Company Settings",
            "path": "/settings/company",
            "order": 1
          },
          {
            "id": "currency-settings",
            "label": "Currency Settings",
            "path": "/settings/currency",
            "order": 2
          },
          {
            "id": "tax-settings",
            "label": "Tax Settings",
            "path": "/settings/tax",
            "order": 3
          },
          {
            "id": "payment-methods",
            "label": "Payment Methods",
            "path": "/settings/payment-methods",
            "order": 4
          },
          {
            "id": "fiscal-year",
            "label": "Fiscal Year",
            "path": "/settings/fiscal-year",
            "order": 5
          },
          {
            "id": "approval-workflows",
            "label": "Approval Workflows",
            "path": "/settings/workflows",
            "order": 6
          }
        ]
      }
    ]
  },
  "task": {
    "moduleId": "task",
    "moduleName": "Task",
    "menus": [
      {
        "id": "dashboard",
        "label": "Dashboard",
        "path": "/",
        "icon": "HomeIcon",
        "order": 1
      },
      {
        "id": "create-ticket",
        "label": "Create Ticket",
        "path": "/create-ticket",
        "icon": "PlusCircleIcon",
        "order": 2
      },
      {
        "id": "my-work",
        "label": "My Work",
        "icon": "UserIcon",
        "order": 3,
        "children": [
          {
            "id": "ticket-queue",
            "label": "Ticket Queue",
            "path": "/ticket-queue",
            "order": 1
          },
          {
            "id": "my-tickets",
            "label": "My Active Tickets",
            "path": "/my-tickets",
            "order": 2
          }
        ]
      },
      {
        "id": "management",
        "label": "Management",
        "icon": "BriefcaseIcon",
        "order": 4,
        "roles": ["manager", "admin"],
        "children": [
          {
            "id": "ticket-pool",
            "label": "Unassigned Pool",
            "path": "/ticket-pool",
            "order": 1
          },
          {
            "id": "assign-tickets",
            "label": "Assign Tickets",
            "path": "/assign-tickets",
            "order": 2
          },
          {
            "id": "all-tickets",
            "label": "All Tickets",
            "path": "/all-tickets",
            "order": 3
          }
        ]
      },
      {
        "id": "administration",
        "label": "Administration",
        "icon": "CogIcon",
        "order": 5,
        "roles": ["admin"],
        "children": [
          {
            "id": "stage-management",
            "label": "Stage Management",
            "path": "/stage-management",
            "order": 1
          }
        ]
      }
    ]
  },
  "health": {
    "moduleId": "health",
    "moduleName": "Healthcare Management",
    "menus": [
      {
        "id": "dashboard",
        "label": "Dashboard",
        "path": "/",
        "icon": "HomeIcon",
        "order": 1
      },
      {
        "id": "patients",
        "label": "Patient Management",
        "icon": "UsersIcon",
        "order": 2,
        "children": [
          {
            "id": "patient-list",
            "label": "View Patients",
            "path": "/patients",
            "order": 1
          },
          {
            "id": "patient-details",
            "label": "Patient Details",
            "path": "/patients/:id",
            "order": 2
          }
        ]
      },
      {
        "id": "contacts",
        "label": "Contacts",
        "icon": "PhoneIcon",
        "path": "/contacts",
        "order": 3
      },
      {
        "id": "appointments",
        "label": "Appointments",
        "icon": "CalendarIcon",
        "path": "/appointments",
        "order": 4
      }
    ]
  }
}
